prt_rl/__init__.py
prt_rl/a2c.py
prt_rl/agent.py
prt_rl/dagger.py
prt_rl/dqn.py
prt_rl/human.py
prt_rl/policy_gradient.py
prt_rl/ppo.py
prt_rl/pretrained.py
prt_rl/random.py
prt_rl/sac.py
prt_rl/td3.py
prt_rl/common/__init__.py
prt_rl/common/activation.py
prt_rl/common/buffers.py
prt_rl/common/collectors.py
prt_rl/common/decision_functions.py
prt_rl/common/distributions.py
prt_rl/common/evaluators.py
prt_rl/common/loggers.py
prt_rl/common/networks.py
prt_rl/common/plot.py
prt_rl/common/progress_bar.py
prt_rl/common/qtable.py
prt_rl/common/recorders.py
prt_rl/common/runners.py
prt_rl/common/schedulers.py
prt_rl/common/trainers.py
prt_rl/common/tuners.py
prt_rl/common/utils.py
prt_rl/common/visualizers.py
prt_rl/common/policies/__init__.py
prt_rl/common/policies/actor_critic.py
prt_rl/common/policies/base.py
prt_rl/common/policies/continuous.py
prt_rl/common/policies/distribution.py
prt_rl/common/policies/qtable.py
prt_rl/common/policies/qvalue.py
prt_rl/common/policies/state_action_critic.py
prt_rl/common/policies/value_critic.py
prt_rl/env/__init__.py
prt_rl/env/interface.py
prt_rl/env/wrappers/__init__.py
prt_rl/env/wrappers/gymnasium_envs.py
prt_rl/env/wrappers/isaaclab_envs.py
prt_rl/env/wrappers/jhu_envs.py
prt_rl/env/wrappers/vmas_envs.py
prt_rl/exact/__init__.py
prt_rl/exact/monte_carlo.py
prt_rl/exact/qlearning.py
prt_rl/exact/sample_average.py
prt_rl/exact/sarsa.py
prt_rl/model_based/__init__.py
prt_rl/model_based/cem.py
prt_rl/model_based/random_shooting.py
prt_rl/model_based/models/__init__.py
prt_rl/model_based/models/cartpole.py
prt_rl/model_based/planners/__init__.py
prt_rl/model_based/planners/cross_entropy.py
prt_rl/model_based/planners/rollout.py
prt_rl/model_based/planners/shooting.py
prt_rl-0.5.8.dist-info/METADATA
prt_rl-0.5.8.dist-info/WHEEL
prt_rl-0.5.8.dist-info/licenses/LICENSE
prt_rl-0.5.8.dist-info/RECORD
