Metadata-Version: 2.4
Name: prt-rl
Version: 0.5.8
Summary: Python Research Toolkit - Reinforcement Learning
Author-email: Gavin Strunk <gavin.strunk@gmail.com>
License-File: LICENSE
Requires-Python: >=3.11
Requires-Dist: boto3>=1.38.3
Requires-Dist: gymnasium>=1.1.1
Requires-Dist: imageio>=2.37.0
Requires-Dist: inputs>=0.5
Requires-Dist: mlflow>=2.20.4
Requires-Dist: optuna>=4.3.0
Requires-Dist: pygame>=2.6.1
Requires-Dist: pynput>=1.8.0
Requires-Dist: pynvml>=12.0.0
Requires-Dist: scipy>=1.15.2
Requires-Dist: torch>=2.6.0
Requires-Dist: tqdm>=4.67.1
Requires-Dist: vmas>=1.5.0
